<Gesture Name="b" Subject="1" Speed="medium" Number="1" NumPts="740" Millseconds="0" AppName="Gestures" AppVer="3.5.0.0" Date="Sunday, July 14, 2024" TimeOfDay="03:01:33 PM"><Point X="287" Y="-76" T="0" /><Point X="287" Y="-77" T="1" /><Point X="287" Y="-79" T="2" /><Point X="287" Y="-80" T="3" /><Point X="287" Y="-81" T="4" /><Point X="286" Y="-82" T="5" /><Point X="286" Y="-83" T="6" /><Point X="286" Y="-84" T="7" /><Point X="286" Y="-91" T="8" /><Point X="285" Y="-92" T="9" /><Point X="285" Y="-93" T="10" /><Point X="285" Y="-95" T="11" /><Point X="285" Y="-96" T="12" /><Point X="284" Y="-100" T="13" /><Point X="284" Y="-101" T="14" /><Point X="284" Y="-103" T="15" /><Point X="284" Y="-105" T="16" /><Point X="284" Y="-106" T="17" /><Point X="284" Y="-108" T="18" /><Point X="283" Y="-110" T="19" /><Point X="282" Y="-139" T="20" /><Point X="281" Y="-150" T="21" /><Point X="281" Y="-153" T="22" /><Point X="281" Y="-156" T="23" /><Point X="281" Y="-159" T="24" /><Point X="281" Y="-162" T="25" /><Point X="281" Y="-165" T="26" /><Point X="280" Y="-181" T="27" /><Point X="280" Y="-184" T="28" /><Point X="280" Y="-187" T="29" /><Point X="280" Y="-191" T="30" /><Point X="279" Y="-194" T="31" /><Point X="279" Y="-205" T="32" /><Point X="279" Y="-209" T="33" /><Point X="279" Y="-212" T="34" /><Point X="279" Y="-216" T="35" /><Point X="279" Y="-219" T="36" /><Point X="279" Y="-223" T="37" /><Point X="279" Y="-230" T="38" /><Point X="279" Y="-234" T="39" /><Point X="279" Y="-237" T="40" /><Point X="279" Y="-241" T="41" /><Point X="279" Y="-244" T="42" /><Point X="279" Y="-248" T="43" /><Point X="279" Y="-251" T="44" /><Point X="279" Y="-255" T="45" /><Point X="280" Y="-265" T="46" /><Point X="280" Y="-269" T="47" /><Point X="281" Y="-273" T="48" /><Point X="281" Y="-276" T="49" /><Point X="281" Y="-280" T="50" /><Point X="282" Y="-284" T="51" /><Point X="282" Y="-287" T="52" /><Point X="283" Y="-294" T="53" /><Point X="283" Y="-298" T="54" /><Point X="283" Y="-301" T="55" /><Point X="284" Y="-305" T="56" /><Point X="284" Y="-308" T="57" /><Point X="285" Y="-312" T="58" /><Point X="285" Y="-315" T="59" /><Point X="286" Y="-328" T="60" /><Point X="287" Y="-331" T="61" /><Point X="287" Y="-335" T="62" /><Point X="288" Y="-338" T="63" /><Point X="288" Y="-341" T="64" /><Point X="289" Y="-350" T="65" /><Point X="289" Y="-353" T="66" /><Point X="289" Y="-356" T="67" /><Point X="290" Y="-359" T="68" /><Point X="290" Y="-362" T="69" /><Point X="290" Y="-365" T="70" /><Point X="290" Y="-367" T="71" /><Point X="291" Y="-373" T="72" /><Point X="291" Y="-376" T="73" /><Point X="291" Y="-379" T="74" /><Point X="292" Y="-381" T="75" /><Point X="292" Y="-384" T="76" /><Point X="292" Y="-387" T="77" /><Point X="292" Y="-389" T="78" /><Point X="293" Y="-399" T="79" /><Point X="293" Y="-402" T="80" /><Point X="294" Y="-404" T="81" /><Point X="294" Y="-407" T="82" /><Point X="294" Y="-409" T="83" /><Point X="295" Y="-416" T="84" /><Point X="295" Y="-419" T="85" /><Point X="295" Y="-421" T="86" /><Point X="296" Y="-423" T="87" /><Point X="296" Y="-426" T="88" /><Point X="296" Y="-428" T="89" /><Point X="296" Y="-430" T="90" /><Point X="297" Y="-442" T="91" /><Point X="297" Y="-444" T="92" /><Point X="297" Y="-446" T="93" /><Point X="297" Y="-448" T="94" /><Point X="298" Y="-457" T="95" /><Point X="298" Y="-459" T="96" /><Point X="298" Y="-460" T="97" /><Point X="298" Y="-462" T="98" /><Point X="298" Y="-464" T="99" /><Point X="298" Y="-466" T="100" /><Point X="298" Y="-470" T="101" /><Point X="298" Y="-471" T="102" /><Point X="299" Y="-473" T="103" /><Point X="299" Y="-474" T="104" /><Point X="299" Y="-476" T="105" /><Point X="299" Y="-477" T="106" /><Point X="299" Y="-478" T="107" /><Point X="299" Y="-480" T="108" /><Point X="299" Y="-483" T="109" /><Point X="299" Y="-484" T="110" /><Point X="299" Y="-485" T="111" /><Point X="299" Y="-486" T="112" /><Point X="299" Y="-487" T="113" /><Point X="299" Y="-488" T="114" /><Point X="299" Y="-489" T="115" /><Point X="299" Y="-488" T="116" /><Point X="299" Y="-487" T="117" /><Point X="299" Y="-486" T="118" /><Point X="298" Y="-485" T="119" /><Point X="297" Y="-480" T="120" /><Point X="297" Y="-478" T="121" /><Point X="297" Y="-477" T="122" /><Point X="296" Y="-475" T="123" /><Point X="296" Y="-473" T="124" /><Point X="294" Y="-467" T="125" /><Point X="294" Y="-464" T="126" /><Point X="293" Y="-462" T="127" /><Point X="293" Y="-459" T="128" /><Point X="292" Y="-456" T="129" /><Point X="291" Y="-453" T="130" /><Point X="290" Y="-450" T="131" /><Point X="289" Y="-443" T="132" /><Point X="288" Y="-439" T="133" /><Point X="288" Y="-435" T="134" /><Point X="287" Y="-432" T="135" /><Point X="286" Y="-428" T="136" /><Point X="286" Y="-423" T="137" /><Point X="285" Y="-419" T="138" /><Point X="283" Y="-402" T="139" /><Point X="283" Y="-398" T="140" /><Point X="282" Y="-394" T="141" /><Point X="282" Y="-385" T="142" /><Point X="281" Y="-381" T="143" /><Point X="281" Y="-369" T="144" /><Point X="281" Y="-365" T="145" /><Point X="281" Y="-362" T="146" /><Point X="281" Y="-358" T="147" /><Point X="281" Y="-354" T="148" /><Point X="281" Y="-351" T="149" /><Point X="281" Y="-335" T="150" /><Point X="281" Y="-331" T="151" /><Point X="282" Y="-328" T="152" /><Point X="282" Y="-325" T="153" /><Point X="282" Y="-322" T="154" /><Point X="284" Y="-313" T="155" /><Point X="284" Y="-310" T="156" /><Point X="284" Y="-306" T="157" /><Point X="284" Y="-303" T="158" /><Point X="285" Y="-300" T="159" /><Point X="285" Y="-297" T="160" /><Point X="286" Y="-293" T="161" /><Point X="286" Y="-286" T="162" /><Point X="287" Y="-283" T="163" /><Point X="287" Y="-279" T="164" /><Point X="288" Y="-276" T="165" /><Point X="288" Y="-272" T="166" /><Point X="289" Y="-269" T="167" /><Point X="289" Y="-265" T="168" /><Point X="290" Y="-251" T="169" /><Point X="290" Y="-247" T="170" /><Point X="291" Y="-244" T="171" /><Point X="291" Y="-240" T="172" /><Point X="291" Y="-237" T="173" /><Point X="292" Y="-227" T="174" /><Point X="292" Y="-223" T="175" /><Point X="292" Y="-220" T="176" /><Point X="292" Y="-217" T="177" /><Point X="293" Y="-214" T="178" /><Point X="293" Y="-211" T="179" /><Point X="293" Y="-208" T="180" /><Point X="293" Y="-205" T="181" /><Point X="293" Y="-203" T="182" /><Point X="293" Y="-200" T="183" /><Point X="293" Y="-198" T="184" /><Point X="293" Y="-195" T="185" /><Point X="293" Y="-193" T="186" /><Point X="293" Y="-190" T="187" /><Point X="294" Y="-188" T="188" /><Point X="295" Y="-180" T="189" /><Point X="295" Y="-178" T="190" /><Point X="295" Y="-176" T="191" /><Point X="296" Y="-171" T="192" /><Point X="296" Y="-169" T="193" /><Point X="297" Y="-165" T="194" /><Point X="297" Y="-163" T="195" /><Point X="298" Y="-162" T="196" /><Point X="298" Y="-160" T="197" /><Point X="299" Y="-158" T="198" /><Point X="299" Y="-156" T="199" /><Point X="299" Y="-154" T="200" /><Point X="300" Y="-152" T="201" /><Point X="301" Y="-144" T="202" /><Point X="302" Y="-142" T="203" /><Point X="302" Y="-140" T="204" /><Point X="303" Y="-139" T="205" /><Point X="303" Y="-137" T="206" /><Point X="304" Y="-133" T="207" /><Point X="304" Y="-132" T="208" /><Point X="305" Y="-130" T="209" /><Point X="305" Y="-128" T="210" /><Point X="305" Y="-126" T="211" /><Point X="306" Y="-125" T="212" /><Point X="306" Y="-123" T="213" /><Point X="306" Y="-121" T="214" /><Point X="307" Y="-120" T="215" /><Point X="307" Y="-118" T="216" /><Point X="307" Y="-116" T="217" /><Point X="308" Y="-115" T="218" /><Point X="308" Y="-113" T="219" /><Point X="308" Y="-112" T="220" /><Point X="309" Y="-110" T="221" /><Point X="309" Y="-109" T="222" /><Point X="310" Y="-105" T="223" /><Point X="310" Y="-104" T="224" /><Point X="310" Y="-103" T="225" /><Point X="311" Y="-101" T="226" /><Point X="311" Y="-100" T="227" /><Point X="311" Y="-99" T="228" /><Point X="312" Y="-96" T="229" /><Point X="312" Y="-95" T="230" /><Point X="312" Y="-94" T="231" /><Point X="312" Y="-93" T="232" /><Point X="312" Y="-92" T="233" /><Point X="313" Y="-91" T="234" /><Point X="313" Y="-88" T="235" /><Point X="314" Y="-87" T="236" /><Point X="314" Y="-86" T="237" /><Point X="315" Y="-84" T="238" /><Point X="315" Y="-83" T="239" /><Point X="316" Y="-83" T="240" /><Point X="316" Y="-82" T="241" /><Point X="318" Y="-81" T="242" /><Point X="318" Y="-80" T="243" /><Point X="319" Y="-80" T="244" /><Point X="321" Y="-79" T="245" /><Point X="322" Y="-79" T="246" /><Point X="323" Y="-79" T="247" /><Point X="324" Y="-79" T="248" /><Point X="325" Y="-79" T="249" /><Point X="326" Y="-79" T="250" /><Point X="328" Y="-79" T="251" /><Point X="330" Y="-79" T="252" /><Point X="331" Y="-79" T="253" /><Point X="332" Y="-79" T="254" /><Point X="334" Y="-79" T="255" /><Point X="335" Y="-79" T="256" /><Point X="342" Y="-79" T="257" /><Point X="343" Y="-79" T="258" /><Point X="345" Y="-79" T="259" /><Point X="347" Y="-79" T="260" /><Point X="348" Y="-80" T="261" /><Point X="352" Y="-80" T="262" /><Point X="354" Y="-80" T="263" /><Point X="356" Y="-80" T="264" /><Point X="358" Y="-80" T="265" /><Point X="360" Y="-80" T="266" /><Point X="362" Y="-80" T="267" /><Point X="364" Y="-81" T="268" /><Point X="372" Y="-81" T="269" /><Point X="374" Y="-81" T="270" /><Point X="376" Y="-81" T="271" /><Point X="378" Y="-81" T="272" /><Point X="379" Y="-81" T="273" /><Point X="385" Y="-81" T="274" /><Point X="387" Y="-81" T="275" /><Point X="388" Y="-81" T="276" /><Point X="389" Y="-81" T="277" /><Point X="390" Y="-81" T="278" /><Point X="393" Y="-81" T="279" /><Point X="394" Y="-81" T="280" /><Point X="395" Y="-81" T="281" /><Point X="396" Y="-81" T="282" /><Point X="397" Y="-81" T="283" /><Point X="398" Y="-81" T="284" /><Point X="399" Y="-82" T="285" /><Point X="401" Y="-82" T="286" /><Point X="406" Y="-84" T="287" /><Point X="407" Y="-84" T="288" /><Point X="408" Y="-84" T="289" /><Point X="409" Y="-85" T="290" /><Point X="410" Y="-85" T="291" /><Point X="412" Y="-86" T="292" /><Point X="413" Y="-87" T="293" /><Point X="414" Y="-87" T="294" /><Point X="415" Y="-88" T="295" /><Point X="416" Y="-89" T="296" /><Point X="417" Y="-89" T="297" /><Point X="418" Y="-90" T="298" /><Point X="419" Y="-91" T="299" /><Point X="423" Y="-94" T="300" /><Point X="424" Y="-95" T="301" /><Point X="425" Y="-95" T="302" /><Point X="426" Y="-96" T="303" /><Point X="427" Y="-97" T="304" /><Point X="431" Y="-100" T="305" /><Point X="432" Y="-101" T="306" /><Point X="433" Y="-102" T="307" /><Point X="434" Y="-103" T="308" /><Point X="435" Y="-104" T="309" /><Point X="436" Y="-105" T="310" /><Point X="437" Y="-106" T="311" /><Point X="439" Y="-108" T="312" /><Point X="441" Y="-109" T="313" /><Point X="442" Y="-110" T="314" /><Point X="443" Y="-111" T="315" /><Point X="444" Y="-112" T="316" /><Point X="445" Y="-113" T="317" /><Point X="446" Y="-114" T="318" /><Point X="450" Y="-118" T="319" /><Point X="450" Y="-119" T="320" /><Point X="451" Y="-120" T="321" /><Point X="452" Y="-121" T="322" /><Point X="453" Y="-122" T="323" /><Point X="454" Y="-123" T="324" /><Point X="456" Y="-125" T="325" /><Point X="456" Y="-126" T="326" /><Point X="457" Y="-127" T="327" /><Point X="458" Y="-128" T="328" /><Point X="459" Y="-129" T="329" /><Point X="459" Y="-130" T="330" /><Point X="460" Y="-131" T="331" /><Point X="463" Y="-134" T="332" /><Point X="463" Y="-135" T="333" /><Point X="464" Y="-136" T="334" /><Point X="464" Y="-137" T="335" /><Point X="465" Y="-138" T="336" /><Point X="465" Y="-139" T="337" /><Point X="467" Y="-143" T="338" /><Point X="467" Y="-144" T="339" /><Point X="467" Y="-145" T="340" /><Point X="468" Y="-146" T="341" /><Point X="468" Y="-147" T="342" /><Point X="468" Y="-149" T="343" /><Point X="469" Y="-151" T="344" /><Point X="469" Y="-153" T="345" /><Point X="469" Y="-154" T="346" /><Point X="470" Y="-155" T="347" /><Point X="470" Y="-157" T="348" /><Point X="470" Y="-158" T="349" /><Point X="470" Y="-159" T="350" /><Point X="470" Y="-161" T="351" /><Point X="470" Y="-164" T="352" /><Point X="470" Y="-166" T="353" /><Point X="470" Y="-167" T="354" /><Point X="470" Y="-168" T="355" /><Point X="470" Y="-170" T="356" /><Point X="470" Y="-171" T="357" /><Point X="470" Y="-172" T="358" /><Point X="470" Y="-173" T="359" /><Point X="470" Y="-175" T="360" /><Point X="470" Y="-176" T="361" /><Point X="470" Y="-177" T="362" /><Point X="470" Y="-179" T="363" /><Point X="470" Y="-180" T="364" /><Point X="470" Y="-181" T="365" /><Point X="469" Y="-182" T="366" /><Point X="468" Y="-187" T="367" /><Point X="468" Y="-189" T="368" /><Point X="468" Y="-190" T="369" /><Point X="467" Y="-191" T="370" /><Point X="467" Y="-193" T="371" /><Point X="466" Y="-194" T="372" /><Point X="465" Y="-198" T="373" /><Point X="464" Y="-199" T="374" /><Point X="464" Y="-201" T="375" /><Point X="463" Y="-202" T="376" /><Point X="462" Y="-203" T="377" /><Point X="462" Y="-205" T="378" /><Point X="461" Y="-206" T="379" /><Point X="458" Y="-211" T="380" /><Point X="458" Y="-213" T="381" /><Point X="457" Y="-214" T="382" /><Point X="456" Y="-215" T="383" /><Point X="456" Y="-217" T="384" /><Point X="453" Y="-221" T="385" /><Point X="453" Y="-222" T="386" /><Point X="452" Y="-224" T="387" /><Point X="451" Y="-225" T="388" /><Point X="450" Y="-227" T="389" /><Point X="450" Y="-228" T="390" /><Point X="449" Y="-230" T="391" /><Point X="448" Y="-231" T="392" /><Point X="447" Y="-232" T="393" /><Point X="447" Y="-234" T="394" /><Point X="446" Y="-235" T="395" /><Point X="444" Y="-237" T="396" /><Point X="444" Y="-238" T="397" /><Point X="443" Y="-240" T="398" /><Point X="442" Y="-241" T="399" /><Point X="438" Y="-247" T="400" /><Point X="437" Y="-248" T="401" /><Point X="436" Y="-249" T="402" /><Point X="435" Y="-250" T="403" /><Point X="434" Y="-252" T="404" /><Point X="432" Y="-254" T="405" /><Point X="431" Y="-255" T="406" /><Point X="430" Y="-256" T="407" /><Point X="429" Y="-257" T="408" /><Point X="428" Y="-258" T="409" /><Point X="427" Y="-260" T="410" /><Point X="426" Y="-261" T="411" /><Point X="425" Y="-262" T="412" /><Point X="420" Y="-266" T="413" /><Point X="419" Y="-267" T="414" /><Point X="418" Y="-268" T="415" /><Point X="416" Y="-269" T="416" /><Point X="415" Y="-270" T="417" /><Point X="410" Y="-274" T="418" /><Point X="409" Y="-275" T="419" /><Point X="407" Y="-276" T="420" /><Point X="406" Y="-277" T="421" /><Point X="405" Y="-278" T="422" /><Point X="403" Y="-279" T="423" /><Point X="402" Y="-280" T="424" /><Point X="401" Y="-281" T="425" /><Point X="399" Y="-282" T="426" /><Point X="398" Y="-283" T="427" /><Point X="397" Y="-284" T="428" /><Point X="395" Y="-285" T="429" /><Point X="394" Y="-286" T="430" /><Point X="392" Y="-287" T="431" /><Point X="387" Y="-291" T="432" /><Point X="385" Y="-292" T="433" /><Point X="384" Y="-293" T="434" /><Point X="382" Y="-294" T="435" /><Point X="381" Y="-294" T="436" /><Point X="379" Y="-295" T="437" /><Point X="376" Y="-297" T="438" /><Point X="375" Y="-298" T="439" /><Point X="373" Y="-298" T="440" /><Point X="372" Y="-299" T="441" /><Point X="370" Y="-300" T="442" /><Point X="369" Y="-300" T="443" /><Point X="367" Y="-301" T="444" /><Point X="366" Y="-302" T="445" /><Point X="360" Y="-304" T="446" /><Point X="358" Y="-304" T="447" /><Point X="357" Y="-305" T="448" /><Point X="355" Y="-305" T="449" /><Point X="354" Y="-306" T="450" /><Point X="348" Y="-307" T="451" /><Point X="346" Y="-307" T="452" /><Point X="345" Y="-308" T="453" /><Point X="343" Y="-308" T="454" /><Point X="342" Y="-308" T="455" /><Point X="341" Y="-308" T="456" /><Point X="339" Y="-308" T="457" /><Point X="338" Y="-309" T="458" /><Point X="336" Y="-309" T="459" /><Point X="335" Y="-309" T="460" /><Point X="333" Y="-309" T="461" /><Point X="332" Y="-309" T="462" /><Point X="330" Y="-309" T="463" /><Point X="329" Y="-309" T="464" /><Point X="327" Y="-309" T="465" /><Point X="321" Y="-309" T="466" /><Point X="319" Y="-309" T="467" /><Point X="318" Y="-309" T="468" /><Point X="316" Y="-309" T="469" /><Point X="315" Y="-309" T="470" /><Point X="311" Y="-310" T="471" /><Point X="310" Y="-310" T="472" /><Point X="308" Y="-310" T="473" /><Point X="306" Y="-310" T="474" /><Point X="304" Y="-310" T="475" /><Point X="303" Y="-310" T="476" /><Point X="301" Y="-310" T="477" /><Point X="293" Y="-310" T="478" /><Point X="292" Y="-310" T="479" /><Point X="290" Y="-310" T="480" /><Point X="289" Y="-311" T="481" /><Point X="287" Y="-311" T="482" /><Point X="283" Y="-311" T="483" /><Point X="282" Y="-311" T="484" /><Point X="280" Y="-311" T="485" /><Point X="279" Y="-311" T="486" /><Point X="278" Y="-311" T="487" /><Point X="277" Y="-311" T="488" /><Point X="275" Y="-312" T="489" /><Point X="274" Y="-312" T="490" /><Point X="273" Y="-312" T="491" /><Point X="272" Y="-312" T="492" /><Point X="271" Y="-312" T="493" /><Point X="270" Y="-312" T="494" /><Point X="271" Y="-312" T="495" /><Point X="272" Y="-312" T="496" /><Point X="274" Y="-311" T="497" /><Point X="275" Y="-311" T="498" /><Point X="276" Y="-311" T="499" /><Point X="277" Y="-310" T="500" /><Point X="280" Y="-309" T="501" /><Point X="281" Y="-309" T="502" /><Point X="282" Y="-309" T="503" /><Point X="283" Y="-309" T="504" /><Point X="284" Y="-308" T="505" /><Point X="285" Y="-308" T="506" /><Point X="287" Y="-308" T="507" /><Point X="295" Y="-306" T="508" /><Point X="297" Y="-306" T="509" /><Point X="299" Y="-305" T="510" /><Point X="301" Y="-305" T="511" /><Point X="311" Y="-303" T="512" /><Point X="313" Y="-302" T="513" /><Point X="316" Y="-302" T="514" /><Point X="319" Y="-301" T="515" /><Point X="321" Y="-301" T="516" /><Point X="324" Y="-300" T="517" /><Point X="330" Y="-299" T="518" /><Point X="333" Y="-299" T="519" /><Point X="336" Y="-298" T="520" /><Point X="339" Y="-298" T="521" /><Point X="343" Y="-297" T="522" /><Point X="346" Y="-297" T="523" /><Point X="349" Y="-296" T="524" /><Point X="352" Y="-296" T="525" /><Point X="366" Y="-294" T="526" /><Point X="369" Y="-294" T="527" /><Point X="372" Y="-293" T="528" /><Point X="376" Y="-293" T="529" /><Point X="379" Y="-293" T="530" /><Point X="386" Y="-292" T="531" /><Point X="393" Y="-291" T="532" /><Point X="396" Y="-291" T="533" /><Point X="400" Y="-291" T="534" /><Point X="404" Y="-290" T="535" /><Point X="407" Y="-290" T="536" /><Point X="425" Y="-290" T="537" /><Point X="429" Y="-290" T="538" /><Point X="433" Y="-290" T="539" /><Point X="436" Y="-290" T="540" /><Point X="440" Y="-290" T="541" /><Point X="451" Y="-290" T="542" /><Point X="454" Y="-291" T="543" /><Point X="458" Y="-291" T="544" /><Point X="461" Y="-292" T="545" /><Point X="465" Y="-292" T="546" /><Point X="471" Y="-293" T="547" /><Point X="478" Y="-294" T="548" /><Point X="481" Y="-294" T="549" /><Point X="484" Y="-294" T="550" /><Point X="486" Y="-295" T="551" /><Point X="489" Y="-295" T="552" /><Point X="492" Y="-296" T="553" /><Point X="495" Y="-296" T="554" /><Point X="504" Y="-298" T="555" /><Point X="506" Y="-299" T="556" /><Point X="509" Y="-299" T="557" /><Point X="511" Y="-300" T="558" /><Point X="512" Y="-300" T="559" /><Point X="517" Y="-302" T="560" /><Point X="519" Y="-302" T="561" /><Point X="520" Y="-303" T="562" /><Point X="522" Y="-303" T="563" /><Point X="523" Y="-304" T="564" /><Point X="524" Y="-304" T="565" /><Point X="525" Y="-305" T="566" /><Point X="530" Y="-308" T="567" /><Point X="531" Y="-308" T="568" /><Point X="532" Y="-309" T="569" /><Point X="534" Y="-311" T="570" /><Point X="535" Y="-311" T="571" /><Point X="536" Y="-312" T="572" /><Point X="537" Y="-313" T="573" /><Point X="538" Y="-314" T="574" /><Point X="539" Y="-315" T="575" /><Point X="540" Y="-316" T="576" /><Point X="540" Y="-317" T="577" /><Point X="541" Y="-317" T="578" /><Point X="541" Y="-318" T="579" /><Point X="543" Y="-320" T="580" /><Point X="543" Y="-321" T="581" /><Point X="543" Y="-322" T="582" /><Point X="544" Y="-322" T="583" /><Point X="544" Y="-324" T="584" /><Point X="545" Y="-325" T="585" /><Point X="545" Y="-326" T="586" /><Point X="545" Y="-327" T="587" /><Point X="546" Y="-328" T="588" /><Point X="546" Y="-331" T="589" /><Point X="547" Y="-332" T="590" /><Point X="547" Y="-333" T="591" /><Point X="547" Y="-334" T="592" /><Point X="547" Y="-337" T="593" /><Point X="547" Y="-338" T="594" /><Point X="547" Y="-339" T="595" /><Point X="547" Y="-340" T="596" /><Point X="547" Y="-341" T="597" /><Point X="548" Y="-342" T="598" /><Point X="548" Y="-343" T="599" /><Point X="548" Y="-344" T="600" /><Point X="548" Y="-345" T="601" /><Point X="548" Y="-346" T="602" /><Point X="548" Y="-347" T="603" /><Point X="548" Y="-348" T="604" /><Point X="548" Y="-349" T="605" /><Point X="548" Y="-354" T="606" /><Point X="548" Y="-355" T="607" /><Point X="548" Y="-356" T="608" /><Point X="547" Y="-357" T="609" /><Point X="547" Y="-358" T="610" /><Point X="546" Y="-360" T="611" /><Point X="546" Y="-361" T="612" /><Point X="546" Y="-362" T="613" /><Point X="545" Y="-363" T="614" /><Point X="545" Y="-364" T="615" /><Point X="545" Y="-365" T="616" /><Point X="544" Y="-366" T="617" /><Point X="543" Y="-368" T="618" /><Point X="541" Y="-373" T="619" /><Point X="541" Y="-374" T="620" /><Point X="540" Y="-376" T="621" /><Point X="539" Y="-377" T="622" /><Point X="539" Y="-379" T="623" /><Point X="536" Y="-383" T="624" /><Point X="536" Y="-385" T="625" /><Point X="535" Y="-386" T="626" /><Point X="534" Y="-388" T="627" /><Point X="533" Y="-390" T="628" /><Point X="532" Y="-391" T="629" /><Point X="530" Y="-395" T="630" /><Point X="529" Y="-396" T="631" /><Point X="528" Y="-398" T="632" /><Point X="527" Y="-400" T="633" /><Point X="527" Y="-401" T="634" /><Point X="525" Y="-403" T="635" /><Point X="523" Y="-406" T="636" /><Point X="522" Y="-408" T="637" /><Point X="519" Y="-412" T="638" /><Point X="517" Y="-414" T="639" /><Point X="516" Y="-415" T="640" /><Point X="515" Y="-417" T="641" /><Point X="514" Y="-418" T="642" /><Point X="512" Y="-420" T="643" /><Point X="509" Y="-422" T="644" /><Point X="508" Y="-424" T="645" /><Point X="507" Y="-425" T="646" /><Point X="505" Y="-426" T="647" /><Point X="503" Y="-427" T="648" /><Point X="502" Y="-429" T="649" /><Point X="500" Y="-430" T="650" /><Point X="492" Y="-436" T="651" /><Point X="490" Y="-437" T="652" /><Point X="488" Y="-439" T="653" /><Point X="486" Y="-440" T="654" /><Point X="485" Y="-441" T="655" /><Point X="479" Y="-444" T="656" /><Point X="477" Y="-445" T="657" /><Point X="475" Y="-447" T="658" /><Point X="473" Y="-448" T="659" /><Point X="471" Y="-449" T="660" /><Point X="470" Y="-450" T="661" /><Point X="460" Y="-455" T="662" /><Point X="458" Y="-456" T="663" /><Point X="456" Y="-457" T="664" /><Point X="455" Y="-459" T="665" /><Point X="451" Y="-461" T="666" /><Point X="446" Y="-464" T="667" /><Point X="444" Y="-465" T="668" /><Point X="442" Y="-466" T="669" /><Point X="440" Y="-466" T="670" /><Point X="438" Y="-467" T="671" /><Point X="437" Y="-468" T="672" /><Point X="433" Y="-470" T="673" /><Point X="431" Y="-471" T="674" /><Point X="429" Y="-471" T="675" /><Point X="428" Y="-472" T="676" /><Point X="426" Y="-473" T="677" /><Point X="424" Y="-473" T="678" /><Point X="422" Y="-474" T="679" /><Point X="415" Y="-476" T="680" /><Point X="413" Y="-477" T="681" /><Point X="411" Y="-477" T="682" /><Point X="409" Y="-477" T="683" /><Point X="408" Y="-478" T="684" /><Point X="406" Y="-478" T="685" /><Point X="402" Y="-479" T="686" /><Point X="400" Y="-479" T="687" /><Point X="398" Y="-479" T="688" /><Point X="396" Y="-479" T="689" /><Point X="394" Y="-480" T="690" /><Point X="392" Y="-480" T="691" /><Point X="390" Y="-480" T="692" /><Point X="380" Y="-480" T="693" /><Point X="377" Y="-480" T="694" /><Point X="375" Y="-481" T="695" /><Point X="373" Y="-481" T="696" /><Point X="366" Y="-481" T="697" /><Point X="364" Y="-481" T="698" /><Point X="362" Y="-481" T="699" /><Point X="360" Y="-481" T="700" /><Point X="358" Y="-481" T="701" /><Point X="357" Y="-481" T="702" /><Point X="355" Y="-481" T="703" /><Point X="351" Y="-481" T="704" /><Point X="350" Y="-481" T="705" /><Point X="348" Y="-481" T="706" /><Point X="346" Y="-481" T="707" /><Point X="345" Y="-481" T="708" /><Point X="343" Y="-481" T="709" /><Point X="341" Y="-481" T="710" /><Point X="334" Y="-480" T="711" /><Point X="332" Y="-480" T="712" /><Point X="330" Y="-480" T="713" /><Point X="328" Y="-480" T="714" /><Point X="326" Y="-480" T="715" /><Point X="325" Y="-479" T="716" /><Point X="321" Y="-479" T="717" /><Point X="319" Y="-479" T="718" /><Point X="317" Y="-479" T="719" /><Point X="315" Y="-479" T="720" /><Point X="313" Y="-479" T="721" /><Point X="311" Y="-478" T="722" /><Point X="309" Y="-478" T="723" /><Point X="302" Y="-478" T="724" /><Point X="300" Y="-478" T="725" /><Point X="299" Y="-478" T="726" /><Point X="297" Y="-478" T="727" /><Point X="295" Y="-478" T="728" /><Point X="290" Y="-478" T="729" /><Point X="288" Y="-478" T="730" /><Point X="287" Y="-478" T="731" /><Point X="286" Y="-478" T="732" /><Point X="284" Y="-478" T="733" /><Point X="283" Y="-478" T="734" /><Point X="282" Y="-478" T="735" /><Point X="281" Y="-478" T="736" /><Point X="280" Y="-478" T="737" /><Point X="279" Y="-478" T="738" /><Point X="279" Y="-478" T="739" /></Gesture>